bm3d_streak_removal/__init__.py
bm3d_streak_removal/_internal.py
bm3d_streak_removal-0.2.0.dist-info/LICENSE
bm3d_streak_removal-0.2.0.dist-info/METADATA
bm3d_streak_removal-0.2.0.dist-info/WHEEL
bm3d_streak_removal-0.2.0.dist-info/top_level.txt
bm3d_streak_removal-0.2.0.dist-info/RECORD
