Metadata-Version: 2.1
Name: bm3d-streak-removal
Version: 0.2.0
Summary: Ring artifact attenuation through multiscale collaborative filtering of correlated noise in sinogram domain
Home-page: UNKNOWN
Author: Ymir Mäkinen
Author-email: ymir.makinen@tuni.fi
License: UNKNOWN
Platform: UNKNOWN
Classifier: Development Status :: 3 - Alpha
Classifier: License :: Free for non-commercial use
Classifier: Intended Audience :: Education
Classifier: Intended Audience :: Science/Research
Classifier: Operating System :: POSIX :: Linux
Classifier: Operating System :: Microsoft :: Windows
Classifier: Operating System :: MacOS
Classifier: Programming Language :: Python :: 3
Classifier: Topic :: Scientific/Engineering :: Information Analysis
Classifier: Topic :: Scientific/Engineering :: Mathematics
Classifier: Topic :: Scientific/Engineering :: Image Processing
Classifier: Topic :: Software Development :: Libraries :: Python Modules
Requires-Python: >=3.5
Requires-Dist: bm3d
Requires-Dist: numpy
Requires-Dist: scipy
